vilocify/__init__.py
vilocify/cli.py
vilocify/http.py
vilocify/jsonapy.py
vilocify/match.py
vilocify/models.py
vilocify/py.typed
vilocify_sdk-0.7.0.dist-info/METADATA
vilocify_sdk-0.7.0.dist-info/WHEEL
vilocify_sdk-0.7.0.dist-info/entry_points.txt
vilocify_sdk-0.7.0.dist-info/licenses/LICENSE
vilocify_sdk-0.7.0.dist-info/RECORD
