Metadata-Version: 2.4
Name: vilocify-sdk
Version: 0.7.0
Summary: Vilocify SDK built atop APIv2
License-Expression: MIT
License-File: LICENSE
Author: Wolfgang Popp
Author-email: popp.wolfgang@siemens.com
Requires-Python: >=3.12,<4.0
Classifier: Programming Language :: Python :: 3
Classifier: Programming Language :: Python :: 3.12
Classifier: Programming Language :: Python :: 3.13
Classifier: Programming Language :: Python :: 3.14
Requires-Dist: click (>=8.1.7,<9.0.0)
Requires-Dist: cyclonedx-python-lib (>=11.0.0,<12.0.0)
Requires-Dist: requests (>=2.31.0,<3.0.0)
Project-URL: Homepage, https://github.com/siemens/vilocify-sdk-python
Project-URL: issues, https://github.com/siemens/vilocify-sdk-python/issues
